MANIFEST.in
README.md
README.rst
UNLICENSE
setup.py
img/shakyo_calligraphy.png
shakyo/__init__.py
shakyo/__main__.py
shakyo/config.py
shakyo/get_args.py
shakyo/log.py
shakyo/path_to_x.py
shakyo/pygments_util.py
shakyo/shakyo.py
shakyo/text_to_lines.py
shakyo/util.py
shakyo.egg-info/PKG-INFO
shakyo.egg-info/SOURCES.txt
shakyo.egg-info/dependency_links.txt
shakyo.egg-info/entry_points.txt
shakyo.egg-info/requires.txt
shakyo.egg-info/top_level.txt
shakyo/consolekit/__init__.py
shakyo/consolekit/attribute.py
shakyo/consolekit/character.py
shakyo/consolekit/console.py
shakyo/consolekit/line.py
shakyo/consolekit/misc.py