Metadata-Version: 1.1
Name: shakyo
Version: 0.0.9
Summary: a tool to learn about something just by typing it
Home-page: http://github.com/raviqqe/shakyo/
Author: raviqqe
Author-email: raviqqe@gmail.com
License: Public Domain
Platform: UNKNOWN
Classifier: Development Status :: 3 - Alpha
Classifier: Environment :: Console :: Curses
Classifier: Intended Audience :: Developers
Classifier: Intended Audience :: End Users/Desktop
Classifier: License :: Public Domain
Classifier: Operating System :: POSIX
Classifier: Programming Language :: Python :: 3.5
Classifier: Topic :: Education :: Computer Aided Instruction (CAI)
Classifier: Topic :: Games/Entertainment
